{
    "keep": {
        "days": true,
        "amount": 14
    },
    "auditLog": "I:\\Mission-3 (Project)\\UM-App2\\logs\\winston\\successes\\.3f56b6ceafea3fb3e60a4dca29250a5ac209565e-audit.json",
    "files": [
        {
            "date": 1688296274872,
            "name": "I:\\Mission-3 (Project)\\UM-App2\\logs\\winston\\successes\\phu-2023-07-02-17-success.log",
            "hash": "b7d896c528e50b60f86c11a7d955198ac6171a0c3af445b7e251b01273c30604"
        },
        {
            "date": 1688299477895,
            "name": "I:\\Mission-3 (Project)\\UM-App2\\logs\\winston\\successes\\phu-2023-07-02-18-success.log",
            "hash": "2a3242b8a9e5d826fdc294f7c89d4ade3f77318e8fcad464f4fa5403c36da57d"
        },
        {
            "date": 1688303885763,
            "name": "I:\\Mission-3 (Project)\\UM-App2\\logs\\winston\\successes\\phu-2023-07-02-19-success.log",
            "hash": "79f5de8354a8bca13163ec6d4fe7bf2a616dbfeb476e8a047e104807df77fd6b"
        },
        {
            "date": 1688320836506,
            "name": "I:\\Mission-3 (Project)\\UM-App2\\logs\\winston\\successes\\phu-2023-07-03-00-success.log",
            "hash": "1f79b06d470c3609f1af83dae9622849dcc05efdad29913b0e27514a0d5b87d0"
        },
        {
            "date": 1688324412123,
            "name": "I:\\Mission-3 (Project)\\UM-App2\\logs\\winston\\successes\\phu-2023-07-03-01-success.log",
            "hash": "d6ca2184c2346ddef2ab7e91491abbfa72f9699da59572dda6ecbbeece3940b6"
        },
        {
            "date": 1688400930869,
            "name": "I:\\Mission-3 (Project)\\UM-App2\\logs\\winston\\successes\\phu-2023-07-03-22-success.log",
            "hash": "e101151ecca8b4ab0fd43080a85d055a1cb0b1541d638fcb8b49100da34102bb"
        },
        {
            "date": 1688404735594,
            "name": "I:\\Mission-3 (Project)\\UM-App2\\logs\\winston\\successes\\phu-2023-07-03-23-success.log",
            "hash": "100f5920efbd014bea44d7c553b34c83c06b066d1b1043cc7ad62a2a54558567"
        },
        {
            "date": 1688407884793,
            "name": "I:\\Mission-3 (Project)\\UM-App2\\logs\\winston\\successes\\phu-2023-07-04-00-success.log",
            "hash": "ae0c47360c578b56dd6688d38abd9ffae19ca50e739c9bc833b7bc5547fda7b8"
        },
        {
            "date": 1688411174885,
            "name": "I:\\Mission-3 (Project)\\UM-App2\\logs\\winston\\successes\\phu-2023-07-04-01-success.log",
            "hash": "d03c3a3d8859b3f0ad6489e3487db01cd6aaad732d0be8411cce20b4be25b279"
        },
        {
            "date": 1688490679859,
            "name": "I:\\Mission-3 (Project)\\UM-App2\\logs\\winston\\successes\\phu-2023-07-04-23-success.log",
            "hash": "94a1b4108034f6b90df257dce42a3a6481800fbfe1be17b3efaf96cf2162af2e"
        },
        {
            "date": 1688493864353,
            "name": "I:\\Mission-3 (Project)\\UM-App2\\logs\\winston\\successes\\phu-2023-07-05-00-success.log",
            "hash": "eb0e8da2aca29dd2761726e3188a71067b8cbf61c63031497d02495e845b5d0b"
        },
        {
            "date": 1688501325514,
            "name": "I:\\Mission-3 (Project)\\UM-App2\\logs\\winston\\successes\\phu-2023-07-05-02-success.log",
            "hash": "5533e8fcae641d1e0bdd60fbed2f2ef3e3c7e6e263ac7f63611502fcece993a0"
        },
        {
            "date": 1688569863323,
            "name": "I:\\Mission-3 (Project)\\UM-App2\\logs\\winston\\successes\\phu-2023-07-05-21-success.log",
            "hash": "d6ec1e450eea2de300de0205cf8014c256f7bf5545aa926886c3eb4f0b6b1461"
        },
        {
            "date": 1688572848222,
            "name": "I:\\Mission-3 (Project)\\UM-App2\\logs\\winston\\successes\\phu-2023-07-05-22-success.log",
            "hash": "5fe8d75ae3522831685b557a6b128ef36aebf77876ad971cf90c1d800235f579"
        },
        {
            "date": 1688576753117,
            "name": "I:\\Mission-3 (Project)\\UM-App2\\logs\\winston\\successes\\phu-2023-07-05-23-success.log",
            "hash": "644a9a021a9ca93362c8709c7a55e65a640c90d9f3b98b454240821f98358322"
        },
        {
            "date": 1688580071475,
            "name": "I:\\Mission-3 (Project)\\UM-App2\\logs\\winston\\successes\\phu-2023-07-06-00-success.log",
            "hash": "37280eef8c6b81b1abb1d8a0c461b9bc5ed633c3e03d67451495dc4aea781e0d"
        },
        {
            "date": 1688583657187,
            "name": "I:\\Mission-3 (Project)\\UM-App2\\logs\\winston\\successes\\phu-2023-07-06-01-success.log",
            "hash": "5d18f9e9d96d680e65604e149a4cc216f5fa21a1da44e54476987f1635bbdba5"
        },
        {
            "date": 1688587580450,
            "name": "I:\\Mission-3 (Project)\\UM-App2\\logs\\winston\\successes\\phu-2023-07-06-02-success.log",
            "hash": "4088a4ca50f16aca2ecdd464ea533987ce7bb97d5b8d3c4005f21d0898dc7bc7"
        },
        {
            "date": 1688664733617,
            "name": "I:\\Mission-3 (Project)\\UM-App2\\logs\\winston\\successes\\phu-2023-07-06-23-success.log",
            "hash": "39bf90fa1b58a7f49256578238b7964483c31021aaa57c86fed9fbcb7b33b1b0"
        },
        {
            "date": 1688667481572,
            "name": "I:\\Mission-3 (Project)\\UM-App2\\logs\\winston\\successes\\phu-2023-07-07-00-success.log",
            "hash": "583cadca179a71f7e07fec6e8713e81cd77fea73143b81caa19ff29871b795ee"
        },
        {
            "date": 1688670373404,
            "name": "I:\\Mission-3 (Project)\\UM-App2\\logs\\winston\\successes\\phu-2023-07-07-01-success.log",
            "hash": "b937b4007888f1a236b3f48dd6e7d82d0e8d88bc68c2e20b66906640de45d677"
        }
    ],
    "hashType": "sha256"
}